<?xml version="1.0" encoding="UTF-8"?>
<!DOCTYPE form-validation PUBLIC 
    "-//Apache Software Foundation//DTD Commons Validator Rules Configuration 1.1//EN" 
    "http://jakarta.apache.org/commons/dtds/validator_1_1.dtd">

<form-validation>

    <formset>
        <form name="Stmcmm001">
        	<field property="userId" depends="required">
        		<arg0 key="아이디는" />
			</field>
			<field property="userKey" depends="required">
                <arg0 key="비밀번호는" />
            </field>        	
        </form>
    </formset>

</form-validation>